dataclass_rest/__init__.py
dataclass_rest/base_client.py
dataclass_rest/boundmethod.py
dataclass_rest/client_protocol.py
dataclass_rest/exceptions.py
dataclass_rest/http_request.py
dataclass_rest/method.py
dataclass_rest/methodspec.py
dataclass_rest/parse_func.py
dataclass_rest/rest.py
dataclass_rest/http/__init__.py
dataclass_rest/http/aiohttp.py
dataclass_rest/http/requests.py
dataclass_rest-0.4.dist-info/METADATA
dataclass_rest-0.4.dist-info/WHEEL
dataclass_rest-0.4.dist-info/top_level.txt
dataclass_rest-0.4.dist-info/RECORD
