Metadata-Version: 2.1
Name: dataclass-rest
Version: 0.4
Summary: An utility for writing simple clients for REST like APIs
Home-page: https://github.com/reagento/dataclass-rest
Author: A. Tikhonov
Author-email: 17@itishka.org
License: Apache2
Classifier: Operating System :: OS Independent
Classifier: Intended Audience :: Developers
Classifier: License :: OSI Approved :: Apache Software License
Classifier: Programming Language :: Python :: 3
Requires-Python: >=3.6
Requires-Dist: adaptix
Requires-Dist: dataclasses ; python_version < "3.7"
Requires-Dist: typing-extensions ; python_version < "3.8"
